toolkit4life/__init__.py
toolkit4life/clients/__init__.py
toolkit4life/clients/_sqlalchemy.py
toolkit4life/clients/postgres.py
toolkit4life/clients/redis.py
toolkit4life/clients/trino.py
toolkit4life/telegram/restrictors.py
toolkit4life/utils/logger.py
toolkit4life/utils/requests.py
toolkit4life/utils/threads.py
toolkit4life-0.2.2.dist-info/LICENSE
toolkit4life-0.2.2.dist-info/METADATA
toolkit4life-0.2.2.dist-info/WHEEL
toolkit4life-0.2.2.dist-info/top_level.txt
toolkit4life-0.2.2.dist-info/RECORD
