Metadata-Version: 2.1
Name: toolkit4life
Version: 0.2.2
Summary: Faster deployment is what we want!
Home-page: https://github.com/keivanipchihagh/toolkit4life
Author: Keivan Ipchi Hagh
Classifier: Programming Language :: Python :: 3
Classifier: License :: OSI Approved :: MIT License
Classifier: Operating System :: OS Independent
Requires-Python: >=3.6
License-File: LICENSE
Requires-Dist: async-timeout
Requires-Dist: certifi
Requires-Dist: charset-normalizer
Requires-Dist: Deprecated
Requires-Dist: greenlet
Requires-Dist: idna
Requires-Dist: numpy
Requires-Dist: packaging
Requires-Dist: pandas
Requires-Dist: psycopg2-binary
Requires-Dist: pyparsing
Requires-Dist: python-dateutil
Requires-Dist: pytz
Requires-Dist: redis
Requires-Dist: requests
Requires-Dist: six
Requires-Dist: SQLAlchemy (==1.4.41)
Requires-Dist: SQLAlchemy-Utils
Requires-Dist: trino
Requires-Dist: urllib3
Requires-Dist: wrapt
Requires-Dist: PyYAML
